gitignore_find-1.2.0.dist-info/METADATA
gitignore_find-1.2.0.dist-info/WHEEL
gitignore_find-1.2.0.dist-info/licenses/LICENSE
gitignore_find/__init__.py
gitignore_find/__init__.pyi
gitignore_find/py.typed
gitignore_find/gitignore_find.pyd
gitignore_find-1.2.0.dist-info/RECORD
