Metadata-Version: 2.4
Name: gitignore-find
Version: 1.2.0
Classifier: Programming Language :: Rust
Classifier: Programming Language :: Python :: Implementation :: CPython
Classifier: Programming Language :: Python :: Implementation :: PyPy
License-File: LICENSE
License-File: LICENSE
Summary: Find all paths in the specified directory that are ignored by .gitignore files
Keywords: git,gitignore,ignore
Author: navyd
Requires-Python: >=3.9
Project-URL: Repository, https://github.com/NavyD/gitignore-find
Project-URL: Changelog, https://github.com/NavyD/gitignore-find/blob/master/CHANGELOG.md
